creatio_activity_monitor/__init__.py
creatio_activity_monitor/__main__.py
creatio_activity_monitor/api.py
creatio_activity_monitor-1.0.0.dist-info/LICENSE
creatio_activity_monitor-1.0.0.dist-info/METADATA
creatio_activity_monitor-1.0.0.dist-info/WHEEL
creatio_activity_monitor-1.0.0.dist-info/entry_points.txt
creatio_activity_monitor-1.0.0.dist-info/RECORD
